[
    {
      "id": 1,
      "name": "Onyx",
      "description": "Onyx Portfolio Environment",
      "fullDescription": "Onyx is my personal website/portfolio that showcases my work, skills, and experiences. The site serves as a central hub for anyone looking to learn more about me and my professional background.",
      "image": "https://obinnanwachukwu.com/projects/Onyx/banner.png",
      "screenshots": ["https://obinnanwachukwu.com/projects/Onyx/s1.png", "https://obinnanwachukwu.com/projects/Onyx/s2.png", "https://obinnanwachukwu.com/projects/Onyx/s3.png", "https://obinnanwachukwu.com/projects/Onyx/s4.png"],
      "canTry": true,
      "trial": "https://obinnanwachukwu.com",
      "github": "https://github.com/ChemicalDaniel/Onyx",
      "releaseDate": "December 2024",
      "icon": "https://obinnanwachukwu.com/projects/Onyx/logo.png"
    }
  ]
