[
    {
      "id": 1,
      "name": "Portfolio",
      "description": "A React website that emulates a desktop environment",
      "fullDescription": "My portfolio is a React app that emulates a Windows-like desktop environment. Its purpose is to show off my resume and projects in a unique and fun way.",
      "image": "https://raw.githubusercontent.com/ChemicalDaniel/website/refs/heads/main/projects/Portfolio/banner.png",
      "screenshots": ["https://raw.githubusercontent.com/ChemicalDaniel/website/refs/heads/main/projects/Portfolio/s1.png"],
      "screenshotdescriptions": ["Welcome Center"],
      "canTry": true,
      "trial": "",
      "icon": "﹫"
    }
  ]
